{
  "objects": {
    "labels": [
      {
        "properties": {
          "fontFamily": {
            "expr": {
              "Literal": {
                "Value": "'''Segoe UI'', wf_segoe-ui_normal, helvetica, arial, sans-serif'"
              }
            }
          },
          "fontSize": {
            "expr": {
              "Literal": {
                "Value": "8D"
              }
            }
          },
          "bold": {
            "expr": {
              "Literal": {
                "Value": "true"
              }
            }
          },
          "color": {
            "solid": {
              "color": {
                "expr": {
                  "Literal": {
                    "Value": "'#63666A'"
                  }
                }
              }
            }
          },
          "labelDisplayUnits": {
            "expr": {
              "Literal": {
                "Value": "1D"
              }
            }
          }
        }
      },
      {
        "properties": {
          "color": {
            "solid": {
              "color": {
                "expr": {
                  "ThemeDataColor": {
                    "ColorId": 2,
                    "Percent": -0.5
                  }
                }
              }
            }
          }
        },
        "selector": {
          "data": [
            {
              "dataViewWildcard": {
                "matchingOption": 1
              }
            }
          ]
        }
      }
    ],
    "categoryLabels": [
      {
        "properties": {
          "show": {
            "expr": {
              "Literal": {
                "Value": "false"
              }
            }
          }
        }
      }
    ]
  },
  "projectionOrdering": {
    "Values": [
      0
    ]
  },
  "queryMetadata": {
    "Select": [
      {
        "Restatement": "Sum of MTD Current Year",
        "Name": "Sum(SorDetail.MTD Current Year)",
        "Type": 1,
        "Format": "\\$#,0;(\\$#,0);\\$#,0"
      }
    ],
    "Filters": [
      {
        "type": 0,
        "expression": {
          "Column": {
            "Expression": {
              "SourceRef": {
                "Entity": "DSR Hierarchy"
              }
            },
            "Property": "Branch"
          }
        }
      },
      {
        "type": 0,
        "expression": {
          "Column": {
            "Expression": {
              "SourceRef": {
                "Entity": "SorMaster"
              }
            },
            "Property": "CancelledFlag"
          }
        }
      },
      {
        "type": 8,
        "expression": {
          "Column": {
            "Expression": {
              "SourceRef": {
                "Entity": "SorMaster"
              }
            },
            "Property": "OrderDate"
          }
        }
      },
      {
        "type": 2,
        "expression": {
          "Aggregation": {
            "Expression": {
              "Column": {
                "Expression": {
                  "SourceRef": {
                    "Entity": "SorDetail"
                  }
                },
                "Property": "MTD Current Year"
              }
            },
            "Function": 0
          }
        }
      },
      {
        "type": 2,
        "expression": {
          "Column": {
            "Expression": {
              "SourceRef": {
                "Entity": "SorDetail"
              }
            },
            "Property": "SorMaster.CustomerPoNumber"
          }
        }
      },
      {
        "type": 2,
        "expression": {
          "Column": {
            "Expression": {
              "SourceRef": {
                "Entity": "SorDetail"
              }
            },
            "Property": "Visual Bookings Value"
          }
        }
      }
    ]
  },
  "visualElements": [
    {
      "DataRoles": [
        {
          "Name": "Values",
          "Projection": 0,
          "isActive": false
        }
      ]
    }
  ],
  "selects": [
    {
      "displayName": "Sum of MTD Current Year",
      "format": "\\$#,0;(\\$#,0);\\$#,0",
      "queryName": "Sum(SorDetail.MTD Current Year)",
      "roles": {
        "Values": true
      },
      "type": {
        "category": null,
        "underlyingType": 259
      },
      "expr": {
        "Aggregation": {
          "Expression": {
            "Column": {
              "Expression": {
                "SourceRef": {
                  "Entity": "SorDetail"
                }
              },
              "Property": "MTD Current Year"
            }
          },
          "Function": 0
        }
      }
    }
  ]
}